README.md
setup.py
BioVirusHost/BioVirusHost.py
BioVirusHost/__init__.py
BioVirusHost.egg-info/PKG-INFO
BioVirusHost.egg-info/SOURCES.txt
BioVirusHost.egg-info/dependency_links.txt
BioVirusHost.egg-info/requires.txt
BioVirusHost.egg-info/top_level.txt