Metadata-Version: 2.1
Name: BioVirusHost
Version: 1.0.1
Summary: A simple Python interface to query the information from Virus-Host DB
Home-page: https://github.com/AliYoussef96/BioVirusHost
Author: Ali Mostafa
Author-email: ali.mo.anwar@std.agr.cu.edu.eg
License: MIT
Platform: UNKNOWN
Classifier: License :: OSI Approved :: MIT License
Classifier: Programming Language :: Python :: 3
Classifier: Intended Audience :: Science/Research
Classifier: Topic :: Scientific/Engineering :: Bio-Informatics
Requires-Python: >=3.7.0
